sdk/__init__.py
zkagi-0.1.0.dist-info/METADATA
zkagi-0.1.0.dist-info/WHEEL
zkagi-0.1.0.dist-info/RECORD
